setup.py
common/__init__.py
common/base_request.py
common/base_response.py
common/base_send_request.py
common/custom_exception.py
common/descriptions.py
common/key_map.py
common/keys_driver.py
sl_api_tools.egg-info/PKG-INFO
sl_api_tools.egg-info/SOURCES.txt
sl_api_tools.egg-info/dependency_links.txt
sl_api_tools.egg-info/requires.txt
sl_api_tools.egg-info/top_level.txt
tools/__init__.py
tools/assert_methods.py
tools/common_methods.py
tools/config.py
tools/excel_tools.py
tools/log.py
tools/mysql_tools.py
tools/post_process_methods.py
tools/random_data.py
tools/utils.py